README.rst
generate_data.py
setup.cfg
setup.py
guess_language/__init__.py
guess_language/__main__.py
guess_language/console_mode.py
guess_language/data/__init__.py
guess_language/data/models/__init__.py
guess_language/data/models/af.py
guess_language/data/models/ar.py
guess_language/data/models/az.py
guess_language/data/models/bg.py
guess_language/data/models/ca.py
guess_language/data/models/ceb.py
guess_language/data/models/cs.py
guess_language/data/models/cy.py
guess_language/data/models/da.py
guess_language/data/models/de.py
guess_language/data/models/en.py
guess_language/data/models/eo.py
guess_language/data/models/es.py
guess_language/data/models/et.py
guess_language/data/models/eu.py
guess_language/data/models/fa.py
guess_language/data/models/fi.py
guess_language/data/models/fr.py
guess_language/data/models/ha.py
guess_language/data/models/haw.py
guess_language/data/models/hi.py
guess_language/data/models/hr.py
guess_language/data/models/hu.py
guess_language/data/models/id.py
guess_language/data/models/is.py
guess_language/data/models/it.py
guess_language/data/models/kk.py
guess_language/data/models/ky.py
guess_language/data/models/la.py
guess_language/data/models/lt.py
guess_language/data/models/lv.py
guess_language/data/models/mk.py
guess_language/data/models/mn.py
guess_language/data/models/nb.py
guess_language/data/models/ne.py
guess_language/data/models/nl.py
guess_language/data/models/nr.py
guess_language/data/models/nso.py
guess_language/data/models/pl.py
guess_language/data/models/ps.py
guess_language/data/models/pt.py
guess_language/data/models/pt_br.py
guess_language/data/models/pt_pt.py
guess_language/data/models/ro.py
guess_language/data/models/ru.py
guess_language/data/models/sk.py
guess_language/data/models/sl.py
guess_language/data/models/so.py
guess_language/data/models/sq.py
guess_language/data/models/sr.py
guess_language/data/models/ss.py
guess_language/data/models/st.py
guess_language/data/models/sv.py
guess_language/data/models/sw.py
guess_language_spirit.egg-info/PKG-INFO
guess_language_spirit.egg-info/SOURCES.txt
guess_language_spirit.egg-info/dependency_links.txt
guess_language_spirit.egg-info/not-zip-safe
guess_language_spirit.egg-info/top_level.txt