Metadata-Version: 1.1
Name: guess-language-spirit
Version: 0.5a5
Summary: Guess the natural language of a text
Home-page: https://bitbucket.org/spirit/guess_language
Author: spirit
Author-email: hiddenspirit@gmail.com
License: UNKNOWN
Download-URL: https://bitbucket.org/spirit/guess_language/downloads
Platform: UNKNOWN
Classifier: Development Status :: 3 - Alpha
Classifier: License :: OSI Approved :: GNU Lesser General Public License v3 or later (LGPLv3+)
Classifier: Programming Language :: Python :: 2.7
Classifier: Programming Language :: Python :: 3
Classifier: Programming Language :: Python :: 3.2
